{
 "edit_history_tweet_ids": [
  "1119328949757198336"
 ],
 "id": "1119328949757198336",
 "text": "Had a great time at #devoxxfr, for me the stand out talks were by @holly_cummins and @speakJava. Had some good chats with lots of cool folk. Definitely gave me a chance to pull my head out of my day-to-day programming and see what else is going on.🖥️\n#quantum #java\n@Work_at_Murex",
 "author_id": "919837946961899520",
 "author": {
  "name": "Helen Wallace",
  "id": "919837946961899520",
  "profile_image_url": "https://pbs.twimg.com/profile_images/1101787858375983105/HfcIBlkR_normal.png",
  "username": "helenFindsLife",
  "created_at": "2017-10-16T08:10:31.000Z",
  "description": "Write Code, clean code.\nClimbing medium rocks.\n\n🖥️🧗‍♀️\n#javaDev #climbingismypassion #andacyclist",
  "imagePath": "HfcIBlkR_normal.png"
 },
 "images": []
}