{
 "edit_history_tweet_ids": [
  "1455574895715303427"
 ],
 "id": "1455574895715303427",
 "author_id": "26448397",
 "text": "@holly_cummins @QCon It was a great talk today. Thanks!",
 "author": {
  "description": "אין הברכה שורה אלא במקום שבו משק הכנפיים נשען על זיעת אפיים, וההשראה נובעת מן השקידה ומן הדקדקנות -- עמוס עוז",
  "profile_image_url": "https://pbs.twimg.com/profile_images/1374615322230202370/hqn_vEiX_normal.jpg",
  "name": "yaron pdut",
  "id": "26448397",
  "created_at": "2009-03-25T06:52:44.000Z",
  "username": "yaronPdut",
  "imagePath": "hqn_vEiX_normal.jpg"
 },
 "images": []
}