{
 "author_id": "924712139608281089",
 "edit_history_tweet_ids": [
  "1549305464122490880"
 ],
 "attachments": {
  "media_keys": [
   "3_1549305422074593280"
  ]
 },
 "text": "Off to a great start of @holly_cummins talk about cloud native https://t.co/IofNdoU6Zg",
 "id": "1549305464122490880",
 "author": {
  "description": "Jakarta EE developer, teacher and Redhatter.",
  "created_at": "2017-10-29T18:58:49.000Z",
  "profile_image_url": "https://pbs.twimg.com/profile_images/945588400693932034/FMBRisPp_normal.jpg",
  "id": "924712139608281089",
  "username": "jeduardobrr",
  "name": "Eduardo Ramírez",
  "imagePath": "FMBRisPp_normal.jpg"
 },
 "images": [
  "FYA9EqNXwAAQdFM.jpg"
 ]
}