{
 "edit_history_tweet_ids": [
  "1144301236482650112"
 ],
 "author_id": "2962482363",
 "id": "1144301236482650112",
 "text": "Argument for introducing testing automation into your business...\n\n@holly_cummins @DOES_EUR #IBMGarage #DOES19 #manualtesting #testingautomation #DevOps https://t.co/29TyNGRysd",
 "author": {
  "username": "ECS_Digi",
  "name": "ECS Digital",
  "description": "Enabling digital transformation since 2003 • Digital Engineering • DevOps training • Agile Testing • Software Development\n\n🐼 Home of the DevOps Playground",
  "id": "2962482363",
  "created_at": "2015-01-05T18:54:06.000Z"
 }
}