{
 "text": "@holly_cummins @Purity_Birir @hot_girl_spring @monkchips @edeandrea Very interesting reading.",
 "id": "1587717050205704192",
 "edit_history_tweet_ids": [
  "1587717050205704192"
 ],
 "author_id": "17258578",
 "author": {
  "id": "17258578",
  "description": "Acid Jazz!!!",
  "name": "Claudio Brogliato",
  "profile_image_url": "https://pbs.twimg.com/profile_images/732588390693109760/hlx-1hLs_normal.jpg",
  "username": "caiodark",
  "created_at": "2008-11-08T20:22:46.000Z",
  "imagePath": "hlx-1hLs_normal.jpg"
 },
 "images": []
}